xladmin/__init__.py
xladmin/adminx.py
xladmin/apps.py
xladmin/filters.py
xladmin/forms.py
xladmin/layout.py
xladmin/models.py
xladmin/sites.py
xladmin/util.py
xladmin/vendors.py
xladmin/widgets.py
xladmin/migrations/0001_initial.py
xladmin/migrations/0002_log.py
xladmin/migrations/0003_auto_20160715_0100.py
xladmin/migrations/0004_alter_bookmark_id_alter_log_id_alter_usersettings_id_and_more.py
xladmin/migrations/__init__.py
xladmin/plugins/__init__.py
xladmin/plugins/actions.py
xladmin/plugins/aggregation.py
xladmin/plugins/ajax.py
xladmin/plugins/auth.py
xladmin/plugins/batch.py
xladmin/plugins/bookmark.py
xladmin/plugins/chart.py
xladmin/plugins/comments.py
xladmin/plugins/details.py
xladmin/plugins/editable.py
xladmin/plugins/export.py
xladmin/plugins/filters.py
xladmin/plugins/images.py
xladmin/plugins/importexport.py
xladmin/plugins/inline.py
xladmin/plugins/language.py
xladmin/plugins/layout.py
xladmin/plugins/mobile.py
xladmin/plugins/multiselect.py
xladmin/plugins/passwords.py
xladmin/plugins/portal.py
xladmin/plugins/quickfilter.py
xladmin/plugins/quickform.py
xladmin/plugins/refresh.py
xladmin/plugins/relate.py
xladmin/plugins/relfield.py
xladmin/plugins/sitemenu.py
xladmin/plugins/sortablelist.py
xladmin/plugins/themes.py
xladmin/plugins/topnav.py
xladmin/plugins/utils.py
xladmin/plugins/wizard.py
xladmin/plugins/xversion.py
xladmin/templatetags/__init__.py
xladmin/templatetags/xadmin_tags.py
xladmin/views/__init__.py
xladmin/views/base.py
xladmin/views/dashboard.py
xladmin/views/delete.py
xladmin/views/detail.py
xladmin/views/edit.py
xladmin/views/form.py
xladmin/views/list.py
xladmin/views/website.py
django_xladmin_enhanced-1.0.6.dist-info/METADATA
django_xladmin_enhanced-1.0.6.dist-info/WHEEL
django_xladmin_enhanced-1.0.6.dist-info/top_level.txt
django_xladmin_enhanced-1.0.6.dist-info/RECORD
