Metadata-Version: 2.4
Name: django-xladmin-enhanced
Version: 1.0.6
Summary: Enhanced Django xAdmin - A modern admin interface for Django
Home-page: https://github.com/yourusername/django-xladmin-enhanced
Author: Enhanced Team
Author-email: your_email@example.com
Classifier: Programming Language :: Python :: 3
Classifier: License :: OSI Approved :: BSD License
Classifier: Operating System :: OS Independent
Classifier: Framework :: Django
Requires-Python: >=3.8
Requires-Dist: Django>=3.2
Requires-Dist: django-crispy-forms
Requires-Dist: crispy-bootstrap3
Requires-Dist: django-import-export
Requires-Dist: django-reversion
Requires-Dist: Pillow
Requires-Dist: future
Requires-Dist: six
Requires-Dist: xlsxwriter
Requires-Dist: xlwt
Requires-Dist: httplib2
Dynamic: author
Dynamic: author-email
Dynamic: classifier
Dynamic: description
Dynamic: description-content-type
Dynamic: home-page
Dynamic: requires-dist
Dynamic: requires-python
Dynamic: summary
